roc_aggregator/__init__.py
roc_aggregator/validations.py
roc_aggregator-1.1.2.dist-info/LICENSE
roc_aggregator-1.1.2.dist-info/METADATA
roc_aggregator-1.1.2.dist-info/WHEEL
roc_aggregator-1.1.2.dist-info/top_level.txt
roc_aggregator-1.1.2.dist-info/RECORD
