Metadata-Version: 2.1
Name: roc-aggregator
Version: 1.1.2
Summary: ROC aggregator
Home-page: https://gitlab.com/UM-CDS/general-tools/roc-aggregator
Author: Pedro Mateus
License: UNKNOWN
Platform: UNKNOWN
Classifier: Programming Language :: Python :: 3
Classifier: License :: OSI Approved :: MIT License
Classifier: Operating System :: OS Independent
License-File: LICENSE
Requires-Dist: numpy (>=1.17)
